{
  "comment": "Epsilon sweep with multiple rankers",
  "grid": {
    "OD.epsilon": [0, 0.2, 0.4],
    "Ranker.rule": ["Random", "Engagement", "Closest", "Narrative", "Diverse_Engagement", "Evil"],
    "Ranker.alpha": [1],
    "Ranker.target_opinion": [0.5]
  },
  "rules": {
    "comment": "Only apply alpha when rule=Engagement, target_opinion when rule=Narrative",
    "conditional_params": {
      "Engagement": ["alpha"],
      "Narrative": ["target_opinion"],
      "Evil": ["target_opinion"],
      "Random": [],
      "Closest": []
    }
  }
}